Metadata-Version: 2.1
Name: libdecsync
Version: 2.1.0.post1
Summary: Python3 bindings for libdecsync
Home-page: https://github.com/39aldo39/libdecsync-bindings-python3
Author: Aldo Gunsing
Author-email: dev@aldogunsing.nl
License: LGPLv2+
Keywords: decsync
Platform: UNKNOWN
Classifier: Programming Language :: Python :: 3
Classifier: Operating System :: POSIX :: Linux
Classifier: Operating System :: Microsoft :: Windows
Classifier: Operating System :: MacOS :: MacOS X
Classifier: License :: OSI Approved :: GNU Lesser General Public License v2 or later (LGPLv2+)
Classifier: Intended Audience :: Developers
License-File: LICENSE.txt
